{
  "confidential": {
  "value": false
  }, 
  "name": "NOVAMAG_theory_TUDA_Co8As24_#71_554",
  "properties": {
    "approach": {
      "value": "theory"
    },
    "summary": {
      "value": "crystal, tetragonal distortion, magnetization, MAE"
    },
    "chemistry": {
      "chemical formula": {
        "value": "Co8As24"
      },
      "production info": {
        "value": "Imposed tetragonal distortion on cubic phase from Materials Project database"
      }
    },
    "crystal": {
      "compound space group": {
        "value": 71
      },
      "unit cell volume": {
        "value": 565.701779
      },
      "lattice parameters": {
        "value": [
          8.18775,
          8.18775,
          8.43838
        ]
      },
      "lattice angles": {
        "value": [
          90.00000,
          90.00000,
          90.00000
        ]
      },
      "atomic positions": {
        "value": [
"Co1(8k)",
0.25000,
0.25000,
0.25000,
"As1(8m)",
0.15199,
0.00000,
0.65879,
"As2(8n)",
0.34121,
0.84801,
0.00000,
"As3(8l)",
0.00000,
0.65879,
0.15199
]
      },
      "crystal info": {
        "value": "1% compressive strain is applied to get the tetragonally distorted structure under the constant volume approximation (unrelaxed crystal structure)"
      }
    },
    "thermodynamics": {
      "unit cell energy": {
        "value": null
      },
      "unit cell formation enthalpy": {
        "value": null
      },
      "energy info": {
        "value": null
      },
      "interatomic potentials info": {
        "value": null
      },
      "magnetic free energy": {
        "value": null
      },
      "magnetic free energy info": {
        "value": null
      }
    },
    "magnetics": {
      "unit cell spin polarization": {
        "value": null
      },
      "atomic spin specie": {
        "value": null
      },
      "saturation magnetization": {
        "value": 6.59217e-05
      },
      "magnetization temperature": {
        "value": 0.0
      },
      "magnetization info": {
        "value": "software VASP (vasp.5.3.3), k-points mesh 6x6x5, Ecut-off=500 eV, PAW_PBE, Co:PAW_PBE:02Aug2007, As:PAW_PBE:22Sep2009"
      },
      "magnetocrystalline anisotropy energy": {
        "value": null
      },
      "anisotropy energy type": {
        "value": "uniaxial"
      },
      "magnetocrystalline anisotropy constants": {
        "value": [5.94763e-05,0.00]
      },
      "kind of anisotropy": {
        "value": null
      },
      "anisotropy info": {
        "value": "software VASP (vasp.5.3.3) with spin-orbit coupling, k-points mesh 6x6x5, Ecut-off=500 eV, PAW_PBE, Co:PAW_PBE:02Aug2007, As:PAW_PBE:22Sep2009"
      },
      "exchange integrals": {
        "value": null
      },
      "exchange info": {
        "value": null
      },
      "magnetic order": {
        "value": null
      },
      "curie temperature": {
        "value": null
      },
      "curie temperature info": {
        "value": null
      },
      "anisotropy field": {
        "value": null
      },
      "remanence": {
        "value": null
      },
      "coercivity": {
        "value": null
      },
      "energy product": {
        "value": null
      },
      "hysteresis info": {
        "value": null
      },
      "domain wall width": {
        "value": null
      },
      "domain wall info": {
        "value": null
      },
      "exchange stiffness": {
        "value": null
      },
      "exchange stiffness info": {
        "value": null
      }
    },
    "additional information": {
      "authors": {
        "value": ["TUDA"]
      },
      "reference": {
        "value": null
      },
      "comments": {
        "value": "A tetragonal distortion was imposed on cubic material by changing the lattice constant in a brute force way, just to find out how the material would change under strain"
      },
      "attached files": {
        "value": [
"Co8As24_#71_554.cif",
"CONTCAR_Co8As24_#71_554",
"Co8As24_#71_554.png"
]
      },
      "attached files info": {
        "value": null
      }
    }
  }
}
