{
  "confidential": {
  "value": false
  }, 
  "name": "NOVAMAG_theory_ICCRAM_Fe12Si4_#65_1",
  "properties": {
    "approach": {
      "value": "theory"
    },
    "summary": {
      "value": "AGA, crystal, energy, magnetization"
    },
    "chemistry": {
      "chemical formula": {
        "value": "Fe12Si4"
      },
      "production info": {
        "value": "obtained by Adaptive Genetic Algorithm Structure Prediction Methods,  software USPEX+VASP"
      }
    },
    "crystal": {
      "compound space group": {
        "value": 65
      },
      "unit cell volume": {
        "value": 173.485970
      },
      "lattice parameters": {
        "value": [
          11.25153,
          5.46259,
          2.82263
        ]
      },
      "lattice angles": {
        "value": [
          90.00000,
          90.00000,
          90.00000
        ]
      },
      "atomic positions": {
        "value": [
"Fe1(4j)",
0.00000,
0.75741,
0.50000,
"Fe2(4g)",
0.62299,
0.00000,
0.00000,
"Fe3(4f)",
0.25000,
0.25000,
0.50000,
"Si1(4g)",
0.13026,
0.00000,
0.00000
]
      },
      "crystal info": {
        "value": "software VASP, k-points mesh 4x7x14, Ecut-off=410.533 eV, PAW_PBE, Fe_pv:PAW_PBE:02Aug2007, Si:PAW_PBE:05Jan2001, Pressure=0.0 kbar,temperature=0K"
      }
    },
    "thermodynamics": {
      "unit cell energy": {
        "value": -124.84234561
      },
      "unit cell formation enthalpy": {
        "value": -4.071303
      },
      "energy info": {
        "value": "software VASP, k-points mesh 4x7x14, Ecut-off=410.533 eV, PAW_PBE, Fe_pv:PAW_PBE:02Aug2007, Si:PAW_PBE:05Jan2001, Pressure=0.0 kbar,temperature=0K"
      },
      "interatomic potentials info": {
        "value": null
      },
      "magnetic free energy": {
        "value": null
      },
      "magnetic free energy info": {
        "value": null
      }
    },
    "magnetics": {
      "unit cell spin polarization": {
        "value": 17.457
      },
      "atomic spin specie": {
        "value": [
"1 Fe",
1.332,
"2 Fe",
1.332,
"3 Fe",
1.332,
"4 Fe",
1.332,
"5 Fe",
2.428,
"6 Fe",
2.428,
"7 Fe",
2.428,
"8 Fe",
2.428,
"9 Fe",
0.659,
"10 Fe",
0.642,
"11 Fe",
0.642,
"12 Fe",
0.660,
"13 Si",
-0.046,
"14 Si",
-0.046,
"15 Si",
-0.046,
"16 Si",
-0.046
]
      },
      "saturation magnetization": {
        "value": 1.172
      },
      "magnetization temperature": {
        "value": 0
      },
      "magnetization info": {
        "value": "software VASP, k-points mesh 4x7x14, Ecut-off=410.533 eV, PAW_PBE, Fe_pv:PAW_PBE:02Aug2007, Si:PAW_PBE:05Jan2001, Pressure=0.0 kbar"
      },
      "magnetocrystalline anisotropy energy": {
        "value": null
      },
      "anisotropy energy type": {
        "value": null
      },
      "magnetocrystalline anisotropy constants": {
        "value": null
      },
      "kind of anisotropy": {
        "value": null
      },
      "anisotropy info": {
        "value": null
      },
      "exchange integrals": {
        "value": null
      },
      "exchange info": {
        "value": null
      },
      "magnetic order": {
        "value": null
      },
      "curie temperature": {
        "value": null
      },
      "curie temperature info": {
        "value": null
      },
      "anisotropy field": {
        "value": null
      },
      "remanence": {
        "value": null
      },
      "coercivity": {
        "value": null
      },
      "energy product": {
        "value": null
      },
      "hysteresis info": {
        "value": null
      },
      "domain wall width": {
        "value": null
      },
      "domain wall info": {
        "value": null
      },
      "exchange stiffness": {
        "value": null
      },
      "exchange stiffness info": {
        "value": null
      }
    },
    "additional information": {
      "authors": {
        "value": ["ICCRAM"]
      },
      "reference": {
        "value": null
      },
      "comments": {
        "value": null
      },
      "attached files": {
        "value": [
"Fe12Si4_#65_1.cif",
"CONTCAR_Fe12Si4_#65_1",
"Fe12Si4_#65_1.png"
]
      },
      "attached files info": {
        "value": null
      }
    }
  }
}
