{
  "confidential": {
  "value": false
  }, 
  "name": "NOVAMAG_theory_ICCRAM_Fe4N1_#12_3",
  "properties": {
    "approach": {
      "value": "theory"
    },
    "summary": {
      "value": "AGA, crystal, energy, magnetization"
    },
    "chemistry": {
      "chemical formula": {
        "value": "Fe4N1"
      },
      "production info": {
        "value": "obtained by Adaptive Genetic Algorithm Structure Prediction Methods,  software USPEX+VASP"
      }
    },
    "crystal": {
      "compound space group": {
        "value": 12
      },
      "unit cell volume": {
        "value": 52.288889
      },
      "lattice parameters": {
        "value": [
          9.19570,
          2.81179,
          4.35300
        ]
      },
      "lattice angles": {
        "value": [
          90.00000,
          111.69819,
          90.00000
        ]
      },
      "atomic positions": {
        "value": [
"Fe1(4i)",
0.37518,
0.00000,
0.09724,
"Fe2(4i)",
0.86238,
0.00000,
0.56295,
"N1(2a)",
0.00000,
0.00000,
0.00000
]
      },
      "crystal info": {
        "value": "software VASP, k-points mesh 10x15x15, Ecut-off=560.000 eV, PAW_PBE, Fe_pv:PAW_PBE:02Aug2007, N:PAW_PBE:08Apr2002, Pressure=0.0 kbar,temperature=0K"
      }
    },
    "thermodynamics": {
      "unit cell energy": {
        "value": -41.30503892
      },
      "unit cell formation enthalpy": {
        "value": 0.059533
      },
      "energy info": {
        "value": "software VASP, k-points mesh 10x15x15, Ecut-off=560.000 eV, PAW_PBE, Fe_pv:PAW_PBE:02Aug2007, N:PAW_PBE:08Apr2002, Pressure=0.0 kbar,temperature=0K"
      },
      "interatomic potentials info": {
        "value": null
      },
      "magnetic free energy": {
        "value": null
      },
      "magnetic free energy info": {
        "value": null
      }
    },
    "magnetics": {
      "unit cell spin polarization": {
        "value": 8.727
      },
      "atomic spin specie": {
        "value": [
"1 Fe",
2.165,
"2 Fe",
2.165,
"3 Fe",
2.245,
"4 Fe",
2.245,
"5 N",
-0.091
]
      },
      "saturation magnetization": {
        "value": 1.944
      },
      "magnetization temperature": {
        "value": 0
      },
      "magnetization info": {
        "value": "software VASP, k-points mesh 10x15x15, Ecut-off=560.000 eV, PAW_PBE, Fe_pv:PAW_PBE:02Aug2007, N:PAW_PBE:08Apr2002, Pressure=0.0 kbar"
      },
      "magnetocrystalline anisotropy energy": {
        "value": null
      },
      "anisotropy energy type": {
        "value": null
      },
      "magnetocrystalline anisotropy constants": {
        "value": null
      },
      "kind of anisotropy": {
        "value": null
      },
      "anisotropy info": {
        "value": null
      },
      "exchange integrals": {
        "value": null
      },
      "exchange info": {
        "value": null
      },
      "magnetic order": {
        "value": null
      },
      "curie temperature": {
        "value": null
      },
      "curie temperature info": {
        "value": null
      },
      "anisotropy field": {
        "value": null
      },
      "remanence": {
        "value": null
      },
      "coercivity": {
        "value": null
      },
      "energy product": {
        "value": null
      },
      "hysteresis info": {
        "value": null
      },
      "domain wall width": {
        "value": null
      },
      "domain wall info": {
        "value": null
      },
      "exchange stiffness": {
        "value": null
      },
      "exchange stiffness info": {
        "value": null
      }
    },
    "additional information": {
      "authors": {
        "value": ["ICCRAM"]
      },
      "reference": {
        "value": null
      },
      "comments": {
        "value": null
      },
      "attached files": {
        "value": [
"Fe4N1_#12_3.cif",
"CONTCAR_Fe4N1_#12_3",
"Fe4N1_#12_3.png"
]
      },
      "attached files info": {
        "value": null
      }
    }
  }
}
